{"entries": [{"description": "", "title": "Gatacca", "subtitle": "", "photo": "b2e976907fa033efebfba8e2a95ac06e.jpeg", "date": 694612620}, {"description": "", "title": "Minority Report", "subtitle": "", "photo": "50a7713b32baba620eb731f963f948d7.jpeg", "date": 696498724.77}, {"description": "", "title": "Nope", "subtitle": "", "photo": "50daa46fe7e0874378ee1f4ab676e3fb.jpeg", "date": 697161231.4200001}, {"description": "", "title": "Children of Men", "subtitle": "", "photo": "426e95cb9df9b50a9e8b106fb3cf347c.jpeg", "date": 698370717.688}, {"description": "", "title": "First Blood", "subtitle": "", "photo": "7ed657e0ac72e727810d80d8ec385f11.jpeg", "date": 699021482.9749999}, {"description": "", "title": "Everything Everywhere all at Once", "subtitle": "", "photo": "d2bed3a215fbf603ccc58f9abfd1bc3d.jpeg", "date": 699194269.326}, {"description": "", "title": "Her", "subtitle": "", "photo": "d4bc363656d0701ec16111e4a7109524.jpeg", "date": 701777489.655}, {"description": "", "title": "Green Room", "subtitle": "", "photo": "a9d290d9a97139c12d27b8a2a8aedcd9.jpeg", "date": 703418959.9130001}, {"description": "", "title": "Air", "subtitle": "", "photo": "a8e7b380d22ff8ad2b1f88d1c9f21e99.jpeg", "date": 704707301.0969999}, {"description": "", "title": "Mission: Impossible- Dead Reckoning", "subtitle": "", "photo": "c8b5470e6dee48a61c253a7ea71ad8d1.jpeg", "date": 711792060.046}, {"description": "", "title": "Oppenheimer", "subtitle": "", "photo": "b42ddf4064273c78d17029db7a5fe6d7.jpeg", "date": 712417200}, {"description": "", "title": "Indiana Jones and the Raiders of the Lost Ark", "subtitle": "", "photo": "e8c7ab305b3be3047961c42d55bbfeae.jpeg", "date": 713624529.786}, {"description": "", "title": "Asteroid City", "subtitle": "", "photo": "ab8b2383ad28326acaf60f196b76f6a9.jpeg", "date": 717681432.8929999}, {"description": "", "title": "Mission Impossible", "subtitle": "", "photo": "e13d2a601e8fcc57180d6bcdd8bd51f4.jpeg", "date": 720186245.1600001}]}